Metadata-Version: 2.1
Name: superbipapteam
Version: 1.0
Summary: SUPER BIPAP Team Module
Home-page: 
Author: Shariat Ullah Pathan
Author-email: superbipap@gmail.com
License: MIT
Keywords: superbipapteam
Classifier: Development Status :: 5 - Production/Stable
Classifier: Intended Audience :: Education
Classifier: Operating System :: Microsoft :: Windows :: Windows 10
Classifier: License :: OSI Approved :: MIT License
Classifier: Programming Language :: Python :: 3
License-File: LICENSE.txt
